Metadata-Version: 1.0
Name: Formula1-data-scraper
Version: 0.0.6
Summary: Package that allows you to collect and store into an AWS postgreSQL RDS, the qualifying and practice data from any formula 1 race weekend from 2006 onwards
Home-page: https://github.com/ishtyaq123/Webscraper_Formula_1_Practice_And_Qualifying_Data.git
Author: Ishtyaq Nabi
Author-email: UNKNOWN
License: MIT
Platform: UNKNOWN
